db_playmate/__init__.py
db_playmate/box.py
db_playmate/cli.py
db_playmate/kobo/__init__.py
db_playmate/kobo/form.py
db_playmate/kobo/kobo.py
db_playmate/kobo/question.py
db_playmate/kobo/submission.py
db_playmate-0.1.0.dist-info/entry_points.txt
db_playmate-0.1.0.dist-info/WHEEL
db_playmate-0.1.0.dist-info/METADATA
db_playmate-0.1.0.dist-info/RECORD
