Metadata-Version: 2.1
Name: db-playmate
Version: 0.1.0
Summary: Client scripts for Databrary PLAY project.
License: GPL-3.0
Author: Shohan Hasan
Author-email: shohan.hasan.x6@gmail.com
Requires-Python: >=3.7,<4.0
Classifier: License :: OSI Approved :: GNU General Public License v3 (GPLv3)
Classifier: Programming Language :: Python :: 3
Classifier: Programming Language :: Python :: 3.7
Requires-Dist: PyJWT (>=1.7,<2.0)
Requires-Dist: boxsdk (>=2.6,<3.0)
Requires-Dist: docutils (>=0.15.2,<0.16.0)
Requires-Dist: flask (>=1.1.1,<2.0.0)
Requires-Dist: furl (>=2.1,<3.0)
Requires-Dist: keyring (>=19.2,<20.0)
Requires-Dist: pytest-cov (>=2.8,<3.0)
Requires-Dist: requests (>=2.22,<3.0)
Requires-Dist: toml (>=0.10.0,<0.11.0)
